spotify_playlist_additions/__init__.py
spotify_playlist_additions/cli.py
spotify_playlist_additions/spotify_playlist_additions.py
spotify_playlist_additions-0.0.1.dist-info/AUTHORS.rst
spotify_playlist_additions-0.0.1.dist-info/LICENSE
spotify_playlist_additions-0.0.1.dist-info/METADATA
spotify_playlist_additions-0.0.1.dist-info/WHEEL
spotify_playlist_additions-0.0.1.dist-info/entry_points.txt
spotify_playlist_additions-0.0.1.dist-info/top_level.txt
spotify_playlist_additions-0.0.1.dist-info/RECORD
