Metadata-Version: 2.1
Name: spotify-playlist-additions
Version: 0.0.1
Summary: A Python implementation of some various different Spotify playlists that I think should alreaydy exist. Fully configurable so you can craft the playlist that you want that acts in the way that you want
Home-page: https://github.com/CoolDudde4150/spotify_playlist_additions
Author: Patrick Christie
Author-email: patrick.christie.dev@gmail.com
License: MIT license
Keywords: spotify_playlist_additions
Platform: UNKNOWN
Classifier: Development Status :: 2 - Pre-Alpha
Classifier: Intended Audience :: Developers
Classifier: License :: OSI Approved :: MIT License
Classifier: Natural Language :: English
Classifier: Programming Language :: Python :: 3
Classifier: Programming Language :: Python :: 3.5
Classifier: Programming Language :: Python :: 3.6
Classifier: Programming Language :: Python :: 3.7
Classifier: Programming Language :: Python :: 3.8
Requires-Python: >=3.5
Requires-Dist: spotipy
